bitprim.py
bitprim-1.1.94.dist-info/METADATA
bitprim-1.1.94.dist-info/RECORD
bitprim-1.1.94.dist-info/WHEEL
bitprim-1.1.94.dist-info/dependency_links.txt
bitprim-1.1.94.dist-info/top_level.txt
