Metadata-Version: 2.1
Name: bitprim
Version: 1.1.94
Summary: Bitcoin development platform
Home-page: https://github.com/bitprim/bitprim-py
Author: Bitprim Inc
Author-email: dev@bitprim.org
License: MIT
Keywords: bitcoin litecoin money bitprim
Platform: UNKNOWN
Classifier: Development Status :: 3 - Alpha
Classifier: Intended Audience :: Developers
Classifier: License :: OSI Approved :: MIT License
Classifier: Natural Language :: English
Classifier: Operating System :: MacOS :: MacOS X
Classifier: Operating System :: POSIX
Classifier: Operating System :: POSIX :: BSD
Classifier: Operating System :: POSIX :: Linux
Classifier: Operating System :: Microsoft :: Windows
Classifier: Programming Language :: Python
Classifier: Programming Language :: Python :: 2
Classifier: Programming Language :: Python :: 2.7
Classifier: Programming Language :: Python :: 3
Classifier: Programming Language :: Python :: 3.3
Classifier: Programming Language :: Python :: 3.4
Classifier: Programming Language :: Python :: 3.5
Classifier: Programming Language :: Python :: 3.6
Classifier: Programming Language :: Python :: Implementation :: CPython
Requires-Dist: conan (>=1.6.1)
Requires-Dist: conan-package-tools (>=0.5.4)
Requires-Dist: bitprim-native (>=1.1.162)
